Workbook
Name Category: Product!$C:$C
Name Cost: Product!#REF!
Name Costs: Footwear_Sales!$I:$I
Name Footwear_Sales: Table1[]
Name Product_Code: Product!$A$1
Name product_name: Product!$B:$B
Name Quantity: Footwear_Sales!$K:$K
Name Sale_productcode: Footwear_Sales!$C:$C
Name Sales: Footwear_Sales!$H:$H
Name sellingPrice: Product!#REF!

Sheet Footwear_Sales
A1: Order ID | B1: Order Date | C1: Product Code | D1: Product Name | E1: Category | F1: Region / Country | G1: Customer Segment | H1: Sales Revenue | I1: Cost | J1: Discount | K1: Quantity
A2: M1000 | B2: 45589 | C2: =INDEX(Product!$A$2:$A$19, MATCH(D2,Product!$B$2:$B$19, 0)) -> P007 | D2: Hiking Boots | E2: Footwear | F2: Germany | G2: Consumer | H2: 22.81 | I2: 16.83 | J2: 0.08 | K2: 1
A3: M1001 | B3: 45632 | C3: =INDEX(Product!$A$2:$A$19, MATCH(D3,Product!$B$2:$B$19, 0)) -> P009 | D3: Jackets | E3: Apparel | F3: Thailand | G3: Consumer | H3: 2476.85 | I3: 1335.03 | J3: 0.12 | K3: 27
A4: M1002 | B4: 45706 | C4: =INDEX(Product!$A$2:$A$19, MATCH(D4,Product!$B$2:$B$19, 0)) -> P002 | D4: Casual Sneakers | E4: Footwear | F4: India | G4: Corporate | H4: 1896.43 | I4: 1358.87 | J4: 0.07 | K4: 29
A5: M1003 | B5: 45477 | C5: =INDEX(Product!$A$2:$A$19, MATCH(D5,Product!$B$2:$B$19, 0)) -> P007 | D5: Hiking Boots | E5: Footwear | F5: Thailand | G5: Home Office | H5: 787.45 | I5: 397.78 | J5: 0.25 | K5: 6
A6: M1004 | B6: 45967 | C6: =INDEX(Product!$A$2:$A$19, MATCH(D6,Product!$B$2:$B$19, 0)) -> P016 | D6: Sunglasses | E6: Accessories | F6: Germany | G6: Consumer | H6: 3248.24 | I6: 1796.55 | J6: 0.13 | K6: 16
A7: M1005 | B7: 45344 | C7: =INDEX(Product!$A$2:$A$19, MATCH(D7,Product!$B$2:$B$19, 0)) -> P004 | D7: Sports Sandals | E7: Footwear | F7: Thailand | G7: Consumer | H7: 889.22 | I7: 512.25 | J7: 0.07 | K7: 20
A8: M1006 | B8: 45823 | C8: =INDEX(Product!$A$2:$A$19, MATCH(D8,Product!$B$2:$B$19, 0)) -> P018 | D8: Track Pants | E8: Apparel | F8: USA | G8: Consumer | H8: 479.54 | I8: 274.68 | J8: 0.19 | K8: 3
A9: M1007 | B9: 45352 | C9: =INDEX(Product!$A$2:$A$19, MATCH(D9,Product!$B$2:$B$19, 0)) -> P008 | D9: T-Shirts | E9: Apparel | F9: USA | G9: Corporate | H9: 2155.97 | I9: 1235.45 | J9: 0.06 | K9: 13
A10: M1008 | B10: 45692 | C10: =INDEX(Product!$A$2:$A$19, MATCH(D10,Product!$B$2:$B$19, 0)) -> P009 | D10: Jackets | E10: Apparel | F10: Australia | G10: Corporate | H10: 1680.66 | I10: 1170.23 | J10: 0.04 | K10: 23
A11: M1009 | B11: 45041 | C11: =INDEX(Product!$A$2:$A$19, MATCH(D11,Product!$B$2:$B$19, 0)) -> P018 | D11: Track Pants | E11: Apparel | F11: USA | G11: Corporate | H11: 5050 | I11: 3272.92 | J11: 0.03 | K11: 28
A12: M1010 | B12: 45894 | C12: =INDEX(Product!$A$2:$A$19, MATCH(D12,Product!$B$2:$B$19, 0)) -> P014 | D12: Socks | E12: Accessories | F12: UK | G12: Consumer | H12: 3546.95 | I12: 1924.69 | J12: 0.03 | K12: 23
A13: M1011 | B13: 45700 | C13: =INDEX(Product!$A$2:$A$19, MATCH(D13,Product!$B$2:$B$19, 0)) -> P016 | D13: Sunglasses | E13: Accessories | F13: USA | G13: Consumer | H13: 2617.3 | I13: 1940.49 | J13: 0.09 | K13: 19
... A3001: M3999 | B3001: 45420 | C3001: =INDEX(Product!$A$2:$A$19, MATCH(D3001,Product!$B$2:$B$19, 0)) -> P011 | D3001: Hoodies | E3001: Apparel | F3001: UK | G3001: Home Office | H3001: 768.6 | I3001: 405.04 | J3001: 0.1 | K3001: 19

Sheet Product
A1: Product Code | B1: Product Name | C1: Category
A2: P001 | B2: Running Shoes Pro | C2: Footwear
A3: P002 | B3: Casual Sneakers | C3: Footwear
A4: P003 | B4: Leather Boots | C4: Footwear
A5: P004 | B5: Sports Sandals | C5: Footwear
A6: P005 | B6: Training Shoes | C6: Footwear
A7: P006 | B7: Flip Flops | C7: Footwear
A8: P007 | B8: Hiking Boots | C8: Footwear
A9: P008 | B9: T-Shirts | C9: Apparel
A10: P009 | B10: Jackets | C10: Apparel
A11: P010 | B11: Shorts | C11: Apparel
A12: P011 | B12: Hoodies | C12: Apparel
... A19: P018 | B19: Track Pants | C19: Apparel

Sheet Customer
A1: Column1 | B1: Column2 | C1: Column3 | D1: Column4 | E1: Column5 | F1: Column6 | G1: Column7
A2: Customer ID | B2: Customer Name | C2: Region | D2: Country | E2: Customer Segment | F2: Age Group | G2: Gender
A3: C001 | B3: John Smith | C3: North Am. | D3: USA | E3: Consumer | F3: 25–34 | G3: Male
A4: C002 | B4: Emma Johnson | C4: Europe | D4: UK | E4: Corporate | F4: 35–44 | G4: Female
A5: C003 | B5: Liam Müller | C5: Europe | D5: Germany | E5: Home Office | F5: 30–39 | G5: Male
A6: C004 | B6: Arjun Patel | C6: Asia | D6: India | E6: Consumer | F6: 18–24 | G6: Male
A7: C005 | B7: Olivia Brown | C7: Oceania | D7: Australia | E7: Corporate | F7: 25–34 | G7: Female
A8: C006 | B8: Niran Chai | C8: Asia | D8: Thailand | E8: Consumer | F8: 20–29 | G8: Male
A9: C007 | B9: Sophia Wilson | C9: North Am. | D9: Canada | E9: Home Office | F9: 30–39 | G9: Female
A10: C008 | B10: Noah Taylor | C10: Europe | D10: UK | E10: Consumer | F10: 18–24 | G10: Male
A11: C009 | B11: Mia Schneider | C11: Europe | D11: Germany | E11: Corporate | F11: 35–44 | G11: Female
A12: C010 | B12: Ethan Davis | C12: North Am. | D12: USA | E12: Consumer | F12: 25–34 | G12: Male
... A17: C015 | B17: Charlotte White | C17: Europe | D17: UK | E17: Home Office | F17: 30–39 | G17: Female
